continuedev/__init__.py
continuedev/__main__.py
continuedev/core/abstract_sdk.py
continuedev/core/autopilot.py
continuedev/core/config.py
continuedev/core/config_utils/context.py
continuedev/core/config_utils/shared.py
continuedev/core/config_utils/step_name_to_class.py
continuedev/core/context.py
continuedev/core/env.py
continuedev/core/lsp.py
continuedev/core/main.py
continuedev/core/models.py
continuedev/core/observation.py
continuedev/core/sdk.py
continuedev/core/steps.py
continuedev/experiments/test.ipynb
continuedev/experiments/y.json
continuedev/headless/__init__.py
continuedev/headless/headless_ide.py
continuedev/libs/__init__.py
continuedev/libs/chroma/.gitignore
continuedev/libs/chroma/update.py
continuedev/libs/constants/default_config.py
continuedev/libs/constants/main.py
continuedev/libs/index/.gitignore
continuedev/libs/index/build_index.py
continuedev/libs/index/chunk_metadata.py
continuedev/libs/index/chunkers/__init__.py
continuedev/libs/index/chunkers/basic.py
continuedev/libs/index/chunkers/chunk.py
continuedev/libs/index/chunkers/chunk_directory.py
continuedev/libs/index/chunkers/code.py
continuedev/libs/index/git.py
continuedev/libs/index/hyde.py
continuedev/libs/index/indices/base.py
continuedev/libs/index/indices/chroma_index.py
continuedev/libs/index/indices/meilisearch_index.py
continuedev/libs/index/indices/mstest.py
continuedev/libs/index/pipelines/main.py
continuedev/libs/index/rerankers/default.py
continuedev/libs/index/rerankers/single_token.py
continuedev/libs/index/update.py
continuedev/libs/index/vectordb.py
continuedev/libs/llm/__init__.py
continuedev/libs/llm/anthropic.py
continuedev/libs/llm/base.py
continuedev/libs/llm/ggml.py
continuedev/libs/llm/google_palm_api.py
continuedev/libs/llm/hf_inference_api.py
continuedev/libs/llm/hf_tgi.py
continuedev/libs/llm/llamacpp.py
continuedev/libs/llm/llamafile.py
continuedev/libs/llm/lmstudio.py
continuedev/libs/llm/ollama.py
continuedev/libs/llm/openai.py
continuedev-0.1.104.dist-info/METADATA
continuedev-0.1.104.dist-info/WHEEL
continuedev-0.1.104.dist-info/entry_points.txt
continuedev-0.1.104.dist-info/RECORD
