Metadata-Version: 2.1
Name: continuedev
Version: 0.1.104
Summary: 
License: Apache-2.0
Author: Nate Sesti
Author-email: sestinj@gmail.com
Requires-Python: >=3.8.1,<4.0.0
Classifier: License :: OSI Approved :: Apache Software License
Classifier: Programming Language :: Python :: 3
Classifier: Programming Language :: Python :: 3.9
Classifier: Programming Language :: Python :: 3.10
Classifier: Programming Language :: Python :: 3.11
Classifier: Programming Language :: Python :: 3.12
Requires-Dist: anthropic (>=0.3.4,<0.4.0)
Requires-Dist: boltons (>=23.0.0,<24.0.0)
Requires-Dist: bs4 (>=0.0.1,<0.0.2)
Requires-Dist: chevron (>=0.14.0,<0.15.0)
Requires-Dist: chromadb (>=0.4.12,<0.5.0)
Requires-Dist: directory-tree (>=0.0.3.1,<0.0.4.0)
Requires-Dist: fastapi (==0.95.2)
Requires-Dist: html2text (>=2020.1.16,<2021.0.0)
Requires-Dist: huggingface-hub (>=0.16.4,<0.17.0)
Requires-Dist: jsonref (>=1.1.0,<2.0.0)
Requires-Dist: jsonschema (>=4.17.3,<5.0.0)
Requires-Dist: meilisearch-python-async (>=1.4.8,<2.0.0)
Requires-Dist: nest-asyncio (>=1.5.6,<2.0.0)
Requires-Dist: openai (>=0.27.5,<0.28.0)
Requires-Dist: pathspec (>=0.11.2,<0.12.0)
Requires-Dist: posthog (>=3.0.1,<4.0.0)
Requires-Dist: psutil (>=5.9.5,<6.0.0)
Requires-Dist: pydantic (>=1.10.8,<2.0.0)
Requires-Dist: pygithub (>=1.59.0,<2.0.0)
Requires-Dist: python-dotenv (>=1.0.0,<2.0.0)
Requires-Dist: python-lsp-server (>=1.7.4,<2.0.0)
Requires-Dist: python-socketio (>=5.10.0,<6.0.0)
Requires-Dist: redbaron (>=0.9.2,<0.10.0)
Requires-Dist: replicate (>=0.11.0,<0.12.0)
Requires-Dist: rich (>=13.6.0,<14.0.0)
Requires-Dist: ripgrepy (>=2.0.0,<3.0.0)
Requires-Dist: socksio (>=1.0.0,<2.0.0)
Requires-Dist: tiktoken (>=0.4.0,<0.5.0)
Requires-Dist: tqdm (>=4.66.1,<5.0.0)
Requires-Dist: tree-sitter (>=0.20.2,<0.21.0)
Requires-Dist: tree-sitter-languages (>=1.7.0,<2.0.0)
Requires-Dist: typer (>=0.9.0,<0.10.0)
Requires-Dist: urllib3 (==1.26.15)
Requires-Dist: uvicorn (>=0.21.1,<0.22.0)
Requires-Dist: websockets (>=11.0.2,<12.0.0)
